{
  "format_version": "1.12.0",
  "minecraft:geometry": [
    {
      "description": {
        "identifier": "geometry.modelshell",
        "texture_width": 256,
        "texture_height": 128,
        "visible_bounds_width": 4,
        "visible_bounds_height": 4,
        "visible_bounds_offset": [
          0,
          1,
          0
        ]
      },
      "bones": [
        {
          "name": "root",
          "pivot": [
            0,
            0,
            0
          ],
          "cubes": [
            {
              "origin": [
                0,
                -3,
                0
              ],
              "size": [
                1,
                12,
                1
              ],
              "uv": [
                0,
                0
              ],
              "mirror": true
            },
            {
              "origin": [
                3,
                -3,
                0
              ],
              "size": [
                1,
                12,
                1
              ],
              "uv": [
                0,
                0
              ],
              "mirror": true
            },
            {
              "origin": [
                1.5,
                -3,
                -1.5
              ],
              "size": [
                1,
                12,
                1
              ],
              "uv": [
                0,
                0
              ],
              "mirror": true
            },
            {
              "origin": [
                1.5,
                -3,
                1.5
              ],
              "size": [
                1,
                12,
                1
              ],
              "uv": [
                0,
                0
              ],
              "mirror": true
            },
            {
              "origin": [
                1.5,
                -4.5,
                -1.5
              ],
              "size": [
                1,
                1,
                1
              ],
              "uv": [
                0,
                0
              ],
              "mirror": true
            },
            {
              "origin": [
                3,
                -4.5,
                0
              ],
              "size": [
                1,
                1,
                1
              ],
              "uv": [
                0,
                0
              ],
              "mirror": true
            },
            {
              "origin": [
                0,
                -4.5,
                0
              ],
              "size": [
                1,
                1,
                1
              ],
              "uv": [
                0,
                0
              ],
              "mirror": true
            },
            {
              "origin": [
                1.5,
                -4.5,
                1.5
              ],
              "size": [
                1,
                1,
                1
              ],
              "uv": [
                0,
                0
              ],
              "mirror": true
            },
            {
              "origin": [
                0.5,
                -4,
                0
              ],
              "size": [
                1,
                15,
                1
              ],
              "uv": [
                0,
                0
              ],
              "mirror": true
            },
            {
              "origin": [
                1.5,
                -4,
                1
              ],
              "size": [
                1,
                15,
                1
              ],
              "uv": [
                0,
                0
              ],
              "mirror": true
            },
            {
              "origin": [
                1.5,
                -4,
                -1
              ],
              "size": [
                1,
                15,
                1
              ],
              "uv": [
                0,
                0
              ],
              "mirror": true
            },
            {
              "origin": [
                2.5,
                -4,
                0
              ],
              "size": [
                1,
                15,
                1
              ],
              "uv": [
                0,
                0
              ],
              "mirror": true
            }
          ]
        },
        {
          "name": "Shell5",
          "pivot": [
            4,
            9,
            1
          ],
          "rotation": [
            0,
            123.5503,
            0
          ],
          "cubes": [
            {
              "origin": [
                4,
                -3,
                1
              ],
              "size": [
                1,
                12,
                1
              ],
              "uv": [
                0,
                0
              ],
              "mirror": true
            }
          ]
        },
        {
          "name": "Shell6",
          "pivot": [
            2.5,
            9,
            2.5
          ],
          "rotation": [
            0,
            -123.5503,
            0
          ],
          "cubes": [
            {
              "origin": [
                2.5,
                -3,
                2.5
              ],
              "size": [
                1,
                12,
                1
              ],
              "uv": [
                0,
                0
              ],
              "mirror": true
            }
          ]
        },
        {
          "name": "Shell7",
          "pivot": [
            2.5,
            9,
            -1.5
          ],
          "rotation": [
            0,
            34.0828,
            0
          ],
          "cubes": [
            {
              "origin": [
                2.5,
                -3,
                -1.5
              ],
              "size": [
                1,
                12,
                1
              ],
              "uv": [
                0,
                0
              ],
              "mirror": true
            }
          ]
        },
        {
          "name": "Shell8",
          "pivot": [
            4,
            9,
            0
          ],
          "rotation": [
            0,
            146.9822,
            0
          ],
          "cubes": [
            {
              "origin": [
                4,
                -3,
                0
              ],
              "size": [
                1,
                12,
                1
              ],
              "uv": [
                0,
                0
              ],
              "mirror": true
            }
          ]
        },
        {
          "name": "Shell9",
          "pivot": [
            1.5,
            9,
            -1.5
          ],
          "rotation": [
            0,
            61.7752,
            0
          ],
          "cubes": [
            {
              "origin": [
                1.5,
                -3,
                -1.5
              ],
              "size": [
                1,
                12,
                1
              ],
              "uv": [
                0,
                0
              ],
              "mirror": true
            }
          ]
        },
        {
          "name": "Shell10",
          "pivot": [
            0,
            9,
            0
          ],
          "rotation": [
            0,
            -59.645,
            0
          ],
          "cubes": [
            {
              "origin": [
                0,
                -3,
                0
              ],
              "size": [
                1,
                12,
                1
              ],
              "uv": [
                0,
                0
              ],
              "mirror": true
            }
          ]
        },
        {
          "name": "Shell11",
          "pivot": [
            0,
            9,
            1
          ],
          "rotation": [
            0,
            -34.0828,
            0
          ],
          "cubes": [
            {
              "origin": [
                0,
                -3,
                1
              ],
              "size": [
                1,
                12,
                1
              ],
              "uv": [
                0,
                0
              ],
              "mirror": true
            }
          ]
        },
        {
          "name": "Shell12",
          "pivot": [
            1.5,
            9,
            2.5
          ],
          "rotation": [
            0,
            -146.9822,
            0
          ],
          "cubes": [
            {
              "origin": [
                1.5,
                -3,
                2.5
              ],
              "size": [
                1,
                12,
                1
              ],
              "uv": [
                0,
                0
              ],
              "mirror": true
            }
          ]
        },
        {
          "name": "Shell16",
          "pivot": [
            1.5,
            -3.5,
            2.5
          ],
          "rotation": [
            0,
            -146.9822,
            0
          ],
          "cubes": [
            {
              "origin": [
                1.5,
                -4.5,
                2.5
              ],
              "size": [
                1,
                1,
                1
              ],
              "uv": [
                0,
                0
              ],
              "mirror": true
            }
          ]
        },
        {
          "name": "Shell18",
          "pivot": [
            0,
            -3.5,
            1
          ],
          "rotation": [
            0,
            -34.0828,
            0
          ],
          "cubes": [
            {
              "origin": [
                0,
                -4.5,
                1
              ],
              "size": [
                1,
                1,
                1
              ],
              "uv": [
                0,
                0
              ],
              "mirror": true
            }
          ]
        },
        {
          "name": "Shell20",
          "pivot": [
            2.5,
            -3.5,
            2.5
          ],
          "rotation": [
            0,
            -123.5503,
            0
          ],
          "cubes": [
            {
              "origin": [
                2.5,
                -4.5,
                2.5
              ],
              "size": [
                1,
                1,
                1
              ],
              "uv": [
                0,
                0
              ],
              "mirror": true
            }
          ]
        },
        {
          "name": "Shell21",
          "pivot": [
            4,
            -3.5,
            1
          ],
          "rotation": [
            0,
            123.5503,
            0
          ],
          "cubes": [
            {
              "origin": [
                4,
                -4.5,
                1
              ],
              "size": [
                1,
                1,
                1
              ],
              "uv": [
                0,
                0
              ],
              "mirror": true
            }
          ]
        },
        {
          "name": "Shell22",
          "pivot": [
            4,
            -3.5,
            0
          ],
          "rotation": [
            0,
            146.9822,
            0
          ],
          "cubes": [
            {
              "origin": [
                4,
                -4.5,
                0
              ],
              "size": [
                1,
                1,
                1
              ],
              "uv": [
                0,
                0
              ],
              "mirror": true
            }
          ]
        },
        {
          "name": "Shell23",
          "pivot": [
            2.5,
            -3.5,
            -1.5
          ],
          "rotation": [
            0,
            34.0828,
            0
          ],
          "cubes": [
            {
              "origin": [
                2.5,
                -4.5,
                -1.5
              ],
              "size": [
                1,
                1,
                1
              ],
              "uv": [
                0,
                0
              ],
              "mirror": true
            }
          ]
        },
        {
          "name": "Shell24",
          "pivot": [
            1.5,
            -3.5,
            -1.5
          ],
          "rotation": [
            0,
            61.7752,
            0
          ],
          "cubes": [
            {
              "origin": [
                1.5,
                -4.5,
                -1.5
              ],
              "size": [
                1,
                1,
                1
              ],
              "uv": [
                0,
                0
              ],
              "mirror": true
            }
          ]
        },
        {
          "name": "Shell25",
          "pivot": [
            0,
            -3.5,
            0
          ],
          "rotation": [
            0,
            -59.645,
            0
          ],
          "cubes": [
            {
              "origin": [
                0,
                -4.5,
                0
              ],
              "size": [
                1,
                1,
                1
              ],
              "uv": [
                0,
                0
              ],
              "mirror": true
            }
          ]
        },
        {
          "name": "Shell30",
          "pivot": [
            0.5,
            11,
            1
          ],
          "rotation": [
            0,
            -46.8639,
            0
          ],
          "cubes": [
            {
              "origin": [
                0.5,
                -4,
                1
              ],
              "size": [
                1,
                15,
                1
              ],
              "uv": [
                0,
                0
              ],
              "mirror": true
            }
          ]
        },
        {
          "name": "Shell31",
          "pivot": [
            1.5,
            11,
            2
          ],
          "rotation": [
            0,
            -136.3314,
            0
          ],
          "cubes": [
            {
              "origin": [
                1.5,
                -4,
                2
              ],
              "size": [
                1,
                15,
                1
              ],
              "uv": [
                0,
                0
              ],
              "mirror": true
            }
          ]
        },
        {
          "name": "Shell32",
          "pivot": [
            2.5,
            11,
            2
          ],
          "rotation": [
            0,
            -134.2012,
            0
          ],
          "cubes": [
            {
              "origin": [
                2.5,
                -4,
                2
              ],
              "size": [
                1,
                15,
                1
              ],
              "uv": [
                0,
                0
              ],
              "mirror": true
            }
          ]
        },
        {
          "name": "Shell33",
          "pivot": [
            3.5,
            11,
            1
          ],
          "rotation": [
            0,
            132.071,
            0
          ],
          "cubes": [
            {
              "origin": [
                3.5,
                -4,
                1
              ],
              "size": [
                1,
                15,
                1
              ],
              "uv": [
                0,
                0
              ],
              "mirror": true
            }
          ]
        },
        {
          "name": "Shell34",
          "pivot": [
            3.5,
            11,
            0
          ],
          "rotation": [
            0,
            134.2012,
            0
          ],
          "cubes": [
            {
              "origin": [
                3.5,
                -4,
                0
              ],
              "size": [
                1,
                15,
                1
              ],
              "uv": [
                0,
                0
              ],
              "mirror": true
            }
          ]
        },
        {
          "name": "Shell35",
          "pivot": [
            2.5,
            11,
            -1
          ],
          "rotation": [
            0,
            44.7337,
            0
          ],
          "cubes": [
            {
              "origin": [
                2.5,
                -4,
                -1
              ],
              "size": [
                1,
                15,
                1
              ],
              "uv": [
                0,
                0
              ],
              "mirror": true
            }
          ]
        },
        {
          "name": "Shell36",
          "pivot": [
            1.5,
            11,
            -1
          ],
          "rotation": [
            0,
            44.7337,
            0
          ],
          "cubes": [
            {
              "origin": [
                1.5,
                -4,
                -1
              ],
              "size": [
                1,
                15,
                1
              ],
              "uv": [
                0,
                0
              ],
              "mirror": true
            }
          ]
        },
        {
          "name": "Shell37",
          "pivot": [
            0.5,
            11,
            0
          ],
          "rotation": [
            0,
            -44.7337,
            0
          ],
          "cubes": [
            {
              "origin": [
                0.5,
                -4,
                0
              ],
              "size": [
                1,
                15,
                1
              ],
              "uv": [
                0,
                0
              ],
              "mirror": true
            }
          ]
        },
        {
          "name": "Shell38",
          "pivot": [
            1.5,
            9,
            -1.5
          ],
          "rotation": [
            -27.6923,
            0,
            0
          ],
          "cubes": [
            {
              "origin": [
                1.5,
                8,
                -1.5
              ],
              "size": [
                1,
                1,
                1
              ],
              "uv": [
                0,
                0
              ],
              "mirror": true
            }
          ]
        },
        {
          "name": "Shell39",
          "pivot": [
            0,
            9,
            0
          ],
          "rotation": [
            0,
            0,
            -27.6923
          ],
          "cubes": [
            {
              "origin": [
                0,
                8,
                0
              ],
              "size": [
                1,
                1,
                1
              ],
              "uv": [
                0,
                0
              ],
              "mirror": true
            }
          ]
        },
        {
          "name": "Shell40",
          "pivot": [
            1.5,
            9,
            2.5
          ],
          "rotation": [
            119.2899,
            0,
            0
          ],
          "cubes": [
            {
              "origin": [
                1.5,
                8,
                2.5
              ],
              "size": [
                1,
                1,
                1
              ],
              "uv": [
                0,
                0
              ],
              "mirror": true
            }
          ]
        },
        {
          "name": "Shell41",
          "pivot": [
            4,
            9,
            0
          ],
          "rotation": [
            0,
            0,
            118.2249
          ],
          "cubes": [
            {
              "origin": [
                4,
                8,
                0
              ],
              "size": [
                1,
                1,
                1
              ],
              "uv": [
                0,
                0
              ],
              "mirror": true
            }
          ]
        }
      ]
    }
  ]
}