{
  "format_version": "1.12.0",
  "minecraft:geometry": [
    {
      "description": {
        "identifier": "geometry.ar15carryhandle",
        "texture_width": 256,
        "texture_height": 128,
        "visible_bounds_width": 4,
        "visible_bounds_height": 4,
        "visible_bounds_offset": [
          0,
          1,
          0
        ]
      },
      "bones": [
        {
          "name": "root",
          "pivot": [
            0,
            0,
            0
          ],
          "cubes": [
            {
              "origin": [
                0,
                11,
                0
              ],
              "size": [
                1,
                3,
                7
              ],
              "uv": [
                0,
                0
              ],
              "mirror": true
            },
            {
              "origin": [
                -5.5,
                11,
                0
              ],
              "size": [
                1,
                3,
                7
              ],
              "uv": [
                0,
                0
              ],
              "mirror": true
            },
            {
              "origin": [
                0,
                14,
                0
              ],
              "size": [
                1,
                2,
                6
              ],
              "uv": [
                0,
                0
              ],
              "mirror": true
            },
            {
              "origin": [
                0,
                11,
                6.3
              ],
              "size": [
                1,
                4,
                1
              ],
              "uv": [
                0,
                0
              ],
              "mirror": true
            },
            {
              "origin": [
                -5.5,
                11,
                6.3
              ],
              "size": [
                1,
                4,
                1
              ],
              "uv": [
                0,
                0
              ],
              "mirror": true
            },
            {
              "origin": [
                -0.2,
                12,
                -29.7
              ],
              "size": [
                1,
                1,
                30
              ],
              "uv": [
                0,
                0
              ],
              "mirror": true
            },
            {
              "origin": [
                -0.2,
                7.8,
                -32.2
              ],
              "size": [
                1,
                4,
                3
              ],
              "uv": [
                0,
                0
              ],
              "mirror": true
            },
            {
              "origin": [
                -0.2,
                13,
                -18
              ],
              "size": [
                1,
                1,
                18
              ],
              "uv": [
                0,
                0
              ],
              "mirror": true
            },
            {
              "origin": [
                -0.2,
                14,
                -6
              ],
              "size": [
                1,
                1,
                6
              ],
              "uv": [
                0,
                0
              ],
              "mirror": true
            },
            {
              "origin": [
                -5.3,
                13,
                -18
              ],
              "size": [
                1,
                1,
                18
              ],
              "uv": [
                0,
                0
              ],
              "mirror": true
            },
            {
              "origin": [
                -5.3,
                12,
                -29.7
              ],
              "size": [
                1,
                1,
                30
              ],
              "uv": [
                0,
                0
              ],
              "mirror": true
            },
            {
              "origin": [
                -5.3,
                14,
                -6
              ],
              "size": [
                1,
                1,
                6
              ],
              "uv": [
                0,
                0
              ],
              "mirror": true
            },
            {
              "origin": [
                -5.3,
                7.8,
                -32.2
              ],
              "size": [
                1,
                4,
                3
              ],
              "uv": [
                0,
                0
              ],
              "mirror": true
            },
            {
              "origin": [
                -5.5,
                14,
                0
              ],
              "size": [
                1,
                2,
                6
              ],
              "uv": [
                0,
                0
              ],
              "mirror": true
            },
            {
              "origin": [
                0,
                11,
                -1.2
              ],
              "size": [
                1,
                5,
                1
              ],
              "uv": [
                0,
                0
              ],
              "mirror": true
            },
            {
              "origin": [
                0,
                11,
                -1.7
              ],
              "size": [
                1,
                5,
                1
              ],
              "uv": [
                0,
                0
              ],
              "mirror": true
            },
            {
              "origin": [
                0,
                14,
                -3.2
              ],
              "size": [
                1,
                2,
                2
              ],
              "uv": [
                0,
                0
              ],
              "mirror": true
            },
            {
              "origin": [
                -5.5,
                14,
                -3.2
              ],
              "size": [
                1,
                2,
                2
              ],
              "uv": [
                0,
                0
              ],
              "mirror": true
            },
            {
              "origin": [
                -5.5,
                11,
                -1.2
              ],
              "size": [
                1,
                5,
                1
              ],
              "uv": [
                0,
                0
              ],
              "mirror": true
            },
            {
              "origin": [
                -5.5,
                11,
                -1.7
              ],
              "size": [
                1,
                5,
                1
              ],
              "uv": [
                0,
                0
              ],
              "mirror": true
            },
            {
              "origin": [
                -0.2,
                7,
                -4.2
              ],
              "size": [
                1,
                5,
                5
              ],
              "uv": [
                0,
                0
              ],
              "mirror": true
            },
            {
              "origin": [
                -5.3,
                7,
                -4.2
              ],
              "size": [
                1,
                5,
                5
              ],
              "uv": [
                0,
                0
              ],
              "mirror": true
            },
            {
              "origin": [
                -1.2,
                10.5,
                0.8
              ],
              "size": [
                2,
                1,
                8
              ],
              "uv": [
                0,
                0
              ],
              "mirror": true
            },
            {
              "origin": [
                -5.3,
                10.5,
                0.8
              ],
              "size": [
                5,
                1,
                8
              ],
              "uv": [
                0,
                0
              ],
              "mirror": true
            },
            {
              "origin": [
                -5.3,
                5.8,
                -32.2
              ],
              "size": [
                5,
                2,
                35
              ],
              "uv": [
                0,
                0
              ],
              "mirror": true
            },
            {
              "origin": [
                -1.2,
                5.8,
                -32.2
              ],
              "size": [
                2,
                2,
                35
              ],
              "uv": [
                0,
                0
              ],
              "mirror": true
            },
            {
              "origin": [
                -6,
                5,
                -32.2
              ],
              "size": [
                1,
                2,
                35
              ],
              "uv": [
                0,
                0
              ],
              "mirror": true
            },
            {
              "origin": [
                0,
                5,
                -32.2
              ],
              "size": [
                2,
                2,
                35
              ],
              "uv": [
                0,
                0
              ],
              "mirror": true
            },
            {
              "origin": [
                1.2,
                3.5,
                -29
              ],
              "size": [
                4,
                5,
                2
              ],
              "uv": [
                0,
                0
              ],
              "mirror": true
            },
            {
              "origin": [
                1.2,
                5,
                -30.5
              ],
              "size": [
                4,
                2,
                5
              ],
              "uv": [
                0,
                0
              ],
              "mirror": true
            },
            {
              "origin": [
                1.2,
                3.5,
                -4
              ],
              "size": [
                4,
                5,
                2
              ],
              "uv": [
                0,
                0
              ],
              "mirror": true
            },
            {
              "origin": [
                1.2,
                5,
                -5.5
              ],
              "size": [
                4,
                2,
                5
              ],
              "uv": [
                0,
                0
              ],
              "mirror": true
            },
            {
              "origin": [
                1.2,
                4,
                -30
              ],
              "size": [
                4,
                4,
                4
              ],
              "uv": [
                0,
                0
              ],
              "mirror": true
            },
            {
              "origin": [
                1.2,
                4,
                -5
              ],
              "size": [
                4,
                4,
                4
              ],
              "uv": [
                0,
                0
              ],
              "mirror": true
            },
            {
              "origin": [
                4.4,
                5,
                -29.2
              ],
              "size": [
                1,
                2,
                2
              ],
              "uv": [
                0,
                0
              ],
              "mirror": true
            },
            {
              "origin": [
                4.4,
                5,
                -4.2
              ],
              "size": [
                1,
                2,
                2
              ],
              "uv": [
                0,
                0
              ],
              "mirror": true
            },
            {
              "origin": [
                -5.3,
                6,
                2
              ],
              "size": [
                5,
                1,
                9
              ],
              "uv": [
                0,
                0
              ],
              "mirror": true
            },
            {
              "origin": [
                -5.3,
                5.5,
                2
              ],
              "size": [
                5,
                1,
                9
              ],
              "uv": [
                0,
                0
              ],
              "mirror": true
            },
            {
              "origin": [
                -1.2,
                6,
                2
              ],
              "size": [
                2,
                1,
                9
              ],
              "uv": [
                0,
                0
              ],
              "mirror": true
            },
            {
              "origin": [
                -1.2,
                5.5,
                2
              ],
              "size": [
                2,
                1,
                9
              ],
              "uv": [
                0,
                0
              ],
              "mirror": true
            },
            {
              "origin": [
                0.3,
                6.5,
                -4.2
              ],
              "size": [
                1,
                2,
                7
              ],
              "uv": [
                0,
                0
              ],
              "mirror": true
            },
            {
              "origin": [
                -5.8,
                6.5,
                -4.2
              ],
              "size": [
                1,
                2,
                7
              ],
              "uv": [
                0,
                0
              ],
              "mirror": true
            },
            {
              "origin": [
                -1.2,
                6.5,
                1
              ],
              "size": [
                2,
                2,
                9
              ],
              "uv": [
                0,
                0
              ],
              "mirror": true
            },
            {
              "origin": [
                -5.3,
                6.5,
                1
              ],
              "size": [
                5,
                2,
                9
              ],
              "uv": [
                0,
                0
              ],
              "mirror": true
            },
            {
              "origin": [
                -0.2,
                8.5,
                7.2
              ],
              "size": [
                1,
                2,
                2
              ],
              "uv": [
                0,
                0
              ],
              "mirror": true
            },
            {
              "origin": [
                -5.3,
                8.5,
                7.2
              ],
              "size": [
                1,
                2,
                2
              ],
              "uv": [
                0,
                0
              ],
              "mirror": true
            },
            {
              "origin": [
                -4.5,
                10.7,
                -3.7
              ],
              "size": [
                5,
                2,
                11
              ],
              "uv": [
                0,
                0
              ],
              "mirror": true
            },
            {
              "origin": [
                -4.5,
                12,
                -30.7
              ],
              "size": [
                5,
                1,
                27
              ],
              "uv": [
                0,
                0
              ],
              "mirror": true
            },
            {
              "origin": [
                -4.5,
                7.6,
                -32.1
              ],
              "size": [
                5,
                4,
                1
              ],
              "uv": [
                0,
                0
              ],
              "mirror": true
            },
            {
              "origin": [
                -4.5,
                11.2,
                1.3
              ],
              "size": [
                5,
                2,
                3
              ],
              "uv": [
                0,
                0
              ],
              "mirror": true
            },
            {
              "origin": [
                -6,
                9.3,
                1
              ],
              "size": [
                5,
                1,
                6
              ],
              "uv": [
                0,
                0
              ],
              "mirror": true
            },
            {
              "origin": [
                -6,
                8.7,
                1
              ],
              "size": [
                5,
                1,
                6
              ],
              "uv": [
                0,
                0
              ],
              "mirror": true
            },
            {
              "origin": [
                -0.5,
                9.3,
                1
              ],
              "size": [
                2,
                1,
                6
              ],
              "uv": [
                0,
                0
              ],
              "mirror": true
            },
            {
              "origin": [
                -0.5,
                8.7,
                1
              ],
              "size": [
                2,
                1,
                6
              ],
              "uv": [
                0,
                0
              ],
              "mirror": true
            },
            {
              "origin": [
                1,
                9.3,
                2
              ],
              "size": [
                1,
                1,
                4
              ],
              "uv": [
                0,
                0
              ],
              "mirror": true
            },
            {
              "origin": [
                -6.5,
                9.3,
                2
              ],
              "size": [
                1,
                1,
                4
              ],
              "uv": [
                0,
                0
              ],
              "mirror": true
            },
            {
              "origin": [
                1,
                8.7,
                2
              ],
              "size": [
                1,
                1,
                4
              ],
              "uv": [
                0,
                0
              ],
              "mirror": true
            },
            {
              "origin": [
                -6.5,
                8.7,
                2
              ],
              "size": [
                1,
                1,
                4
              ],
              "uv": [
                0,
                0
              ],
              "mirror": true
            },
            {
              "origin": [
                -4.25,
                7.5,
                2
              ],
              "size": [
                4,
                4,
                4
              ],
              "uv": [
                0,
                0
              ],
              "mirror": true
            },
            {
              "origin": [
                -7.5,
                11,
                3
              ],
              "size": [
                2,
                4,
                2
              ],
              "uv": [
                0,
                0
              ],
              "mirror": true
            },
            {
              "origin": [
                -7.5,
                12,
                2
              ],
              "size": [
                2,
                2,
                4
              ],
              "uv": [
                0,
                0
              ],
              "mirror": true
            },
            {
              "origin": [
                -7.5,
                13.7,
                2.4
              ],
              "size": [
                2,
                1,
                1
              ],
              "uv": [
                0,
                0
              ],
              "mirror": true
            },
            {
              "origin": [
                -7.5,
                11.3,
                2.4
              ],
              "size": [
                2,
                1,
                1
              ],
              "uv": [
                0,
                0
              ],
              "mirror": true
            },
            {
              "origin": [
                -7.5,
                13.7,
                4.7
              ],
              "size": [
                2,
                1,
                1
              ],
              "uv": [
                0,
                0
              ],
              "mirror": true
            },
            {
              "origin": [
                -7.5,
                11.3,
                4.7
              ],
              "size": [
                2,
                1,
                1
              ],
              "uv": [
                0,
                0
              ],
              "mirror": true
            },
            {
              "origin": [
                0.2,
                12,
                3
              ],
              "size": [
                1,
                2,
                2
              ],
              "uv": [
                0,
                0
              ],
              "mirror": true
            },
            {
              "origin": [
                0.2,
                13.2,
                3.5
              ],
              "size": [
                1,
                1,
                1
              ],
              "uv": [
                0,
                0
              ],
              "mirror": true
            },
            {
              "origin": [
                0.2,
                11.8,
                3.5
              ],
              "size": [
                1,
                1,
                1
              ],
              "uv": [
                0,
                0
              ],
              "mirror": true
            },
            {
              "origin": [
                0.2,
                12.5,
                2.8
              ],
              "size": [
                1,
                1,
                1
              ],
              "uv": [
                0,
                0
              ],
              "mirror": true
            },
            {
              "origin": [
                0.2,
                12.5,
                4.2
              ],
              "size": [
                1,
                1,
                1
              ],
              "uv": [
                0,
                0
              ],
              "mirror": true
            }
          ]
        },
        {
          "name": "CarryHandle4",
          "pivot": [
            0,
            16.5,
            0
          ],
          "rotation": [
            -4.2604,
            0,
            0
          ],
          "cubes": [
            {
              "origin": [
                0,
                15.5,
                0
              ],
              "size": [
                1,
                1,
                5
              ],
              "uv": [
                0,
                0
              ],
              "mirror": true
            }
          ]
        },
        {
          "name": "CarryHandle6",
          "pivot": [
            0,
            16.8,
            5
          ],
          "rotation": [
            25.5621,
            0,
            0
          ],
          "cubes": [
            {
              "origin": [
                0,
                15.8,
                5
              ],
              "size": [
                1,
                1,
                1
              ],
              "uv": [
                0,
                0
              ],
              "mirror": true
            }
          ]
        },
        {
          "name": "CarryHandle8",
          "pivot": [
            0,
            16.3,
            5.9
          ],
          "rotation": [
            44.7337,
            0,
            0
          ],
          "cubes": [
            {
              "origin": [
                0,
                14.3,
                5.9
              ],
              "size": [
                1,
                2,
                2
              ],
              "uv": [
                0,
                0
              ],
              "mirror": true
            }
          ]
        },
        {
          "name": "CarryHandle11",
          "pivot": [
            -0.2,
            16.5,
            0
          ],
          "rotation": [
            85.2071,
            0,
            0
          ],
          "cubes": [
            {
              "origin": [
                -0.2,
                -13.5,
                0
              ],
              "size": [
                1,
                30,
                2
              ],
              "uv": [
                0,
                0
              ],
              "mirror": true
            }
          ]
        },
        {
          "name": "CarryHandle13",
          "pivot": [
            -0.2,
            13.7,
            -29.9
          ],
          "rotation": [
            51.1243,
            0,
            0
          ],
          "cubes": [
            {
              "origin": [
                -0.2,
                10.7,
                -29.9
              ],
              "size": [
                1,
                3,
                2
              ],
              "uv": [
                0,
                0
              ],
              "mirror": true
            }
          ]
        },
        {
          "name": "CarryHandle19",
          "pivot": [
            -5.3,
            16.5,
            0
          ],
          "rotation": [
            85.2071,
            0,
            0
          ],
          "cubes": [
            {
              "origin": [
                -5.3,
                -13.5,
                0
              ],
              "size": [
                1,
                30,
                2
              ],
              "uv": [
                0,
                0
              ],
              "mirror": true
            }
          ]
        },
        {
          "name": "CarryHandle21",
          "pivot": [
            -5.3,
            13.7,
            -29.9
          ],
          "rotation": [
            51.1243,
            0,
            0
          ],
          "cubes": [
            {
              "origin": [
                -5.3,
                10.7,
                -29.9
              ],
              "size": [
                1,
                3,
                2
              ],
              "uv": [
                0,
                0
              ],
              "mirror": true
            }
          ]
        },
        {
          "name": "CarryHandle23",
          "pivot": [
            -5.5,
            16.3,
            5.9
          ],
          "rotation": [
            44.7337,
            0,
            0
          ],
          "cubes": [
            {
              "origin": [
                -5.5,
                14.3,
                5.9
              ],
              "size": [
                1,
                2,
                2
              ],
              "uv": [
                0,
                0
              ],
              "mirror": true
            }
          ]
        },
        {
          "name": "CarryHandle24",
          "pivot": [
            -5.5,
            16.8,
            5
          ],
          "rotation": [
            25.5621,
            0,
            0
          ],
          "cubes": [
            {
              "origin": [
                -5.5,
                15.8,
                5
              ],
              "size": [
                1,
                1,
                1
              ],
              "uv": [
                0,
                0
              ],
              "mirror": true
            }
          ]
        },
        {
          "name": "CarryHandle25",
          "pivot": [
            -5.5,
            16.5,
            0
          ],
          "rotation": [
            -4.2604,
            0,
            0
          ],
          "cubes": [
            {
              "origin": [
                -5.5,
                15.5,
                0
              ],
              "size": [
                1,
                1,
                5
              ],
              "uv": [
                0,
                0
              ],
              "mirror": true
            }
          ]
        },
        {
          "name": "CarryHandle27",
          "pivot": [
            0,
            16.5,
            -0.2
          ],
          "rotation": [
            85.2071,
            0,
            0
          ],
          "cubes": [
            {
              "origin": [
                0,
                13.5,
                -0.2
              ],
              "size": [
                1,
                3,
                1
              ],
              "uv": [
                0,
                0
              ],
              "mirror": true
            }
          ]
        },
        {
          "name": "CarryHandle31",
          "pivot": [
            0,
            14,
            -3.2
          ],
          "rotation": [
            -25.5621,
            0,
            0
          ],
          "cubes": [
            {
              "origin": [
                0,
                11,
                -3.2
              ],
              "size": [
                1,
                3,
                2
              ],
              "uv": [
                0,
                0
              ],
              "mirror": true
            }
          ]
        },
        {
          "name": "CarryHandle32",
          "pivot": [
            0,
            11,
            -1.7
          ],
          "rotation": [
            -119.2899,
            0,
            0
          ],
          "cubes": [
            {
              "origin": [
                0,
                10,
                -1.7
              ],
              "size": [
                1,
                1,
                1
              ],
              "uv": [
                0,
                0
              ],
              "mirror": true
            }
          ]
        },
        {
          "name": "CarryHandle33",
          "pivot": [
            -5.5,
            16.5,
            -0.2
          ],
          "rotation": [
            85.2071,
            0,
            0
          ],
          "cubes": [
            {
              "origin": [
                -5.5,
                13.5,
                -0.2
              ],
              "size": [
                1,
                3,
                1
              ],
              "uv": [
                0,
                0
              ],
              "mirror": true
            }
          ]
        },
        {
          "name": "CarryHandle35",
          "pivot": [
            -5.5,
            14,
            -3.2
          ],
          "rotation": [
            -25.5621,
            0,
            0
          ],
          "cubes": [
            {
              "origin": [
                -5.5,
                11,
                -3.2
              ],
              "size": [
                1,
                3,
                2
              ],
              "uv": [
                0,
                0
              ],
              "mirror": true
            }
          ]
        },
        {
          "name": "CarryHandle36",
          "pivot": [
            -5.5,
            11,
            -1.7
          ],
          "rotation": [
            -119.2899,
            0,
            0
          ],
          "cubes": [
            {
              "origin": [
                -5.5,
                10,
                -1.7
              ],
              "size": [
                1,
                1,
                1
              ],
              "uv": [
                0,
                0
              ],
              "mirror": true
            }
          ]
        },
        {
          "name": "CarryHandle59",
          "pivot": [
            4.3,
            7.5,
            -30.2
          ],
          "rotation": [
            -44.7337,
            0,
            0
          ],
          "cubes": [
            {
              "origin": [
                4.3,
                2.5,
                -30.2
              ],
              "size": [
                1,
                5,
                1
              ],
              "uv": [
                0,
                0
              ],
              "mirror": true
            }
          ]
        },
        {
          "name": "CarryHandle60",
          "pivot": [
            4.3,
            7.5,
            -5.2
          ],
          "rotation": [
            -44.7337,
            0,
            0
          ],
          "cubes": [
            {
              "origin": [
                4.3,
                2.5,
                -5.2
              ],
              "size": [
                1,
                5,
                1
              ],
              "uv": [
                0,
                0
              ],
              "mirror": true
            }
          ]
        },
        {
          "name": "CarryHandle63",
          "pivot": [
            -5.3,
            11.5,
            8.8
          ],
          "rotation": [
            63.9053,
            0,
            0
          ],
          "cubes": [
            {
              "origin": [
                -5.3,
                10.5,
                8.8
              ],
              "size": [
                5,
                1,
                6
              ],
              "uv": [
                0,
                0
              ],
              "mirror": true
            }
          ]
        },
        {
          "name": "CarryHandle66",
          "pivot": [
            -1.2,
            11.5,
            8.8
          ],
          "rotation": [
            63.9053,
            0,
            0
          ],
          "cubes": [
            {
              "origin": [
                -1.2,
                10.5,
                8.8
              ],
              "size": [
                2,
                1,
                6
              ],
              "uv": [
                0,
                0
              ],
              "mirror": true
            }
          ]
        },
        {
          "name": "CarryHandle71",
          "pivot": [
            0.3,
            8.5,
            -4.2
          ],
          "rotation": [
            66.0355,
            0,
            0
          ],
          "cubes": [
            {
              "origin": [
                0.3,
                4.5,
                -4.2
              ],
              "size": [
                1,
                4,
                2
              ],
              "uv": [
                0,
                0
              ],
              "mirror": true
            }
          ]
        },
        {
          "name": "CarryHandle72",
          "pivot": [
            -5.8,
            8.5,
            -4.2
          ],
          "rotation": [
            66.0355,
            0,
            0
          ],
          "cubes": [
            {
              "origin": [
                -5.8,
                4.5,
                -4.2
              ],
              "size": [
                1,
                4,
                2
              ],
              "uv": [
                0,
                0
              ],
              "mirror": true
            }
          ]
        },
        {
          "name": "CarryHandle79",
          "pivot": [
            -4.5,
            13,
            -30.7
          ],
          "rotation": [
            46.8639,
            0,
            0
          ],
          "cubes": [
            {
              "origin": [
                -4.5,
                11,
                -30.7
              ],
              "size": [
                5,
                2,
                1
              ],
              "uv": [
                0,
                0
              ],
              "mirror": true
            }
          ]
        },
        {
          "name": "CarryHandle82",
          "pivot": [
            -4.5,
            13.2,
            4.3
          ],
          "rotation": [
            36.213,
            0,
            0
          ],
          "cubes": [
            {
              "origin": [
                -4.5,
                12.2,
                4.3
              ],
              "size": [
                5,
                1,
                2
              ],
              "uv": [
                0,
                0
              ],
              "mirror": true
            }
          ]
        }
      ]
    }
  ]
}