{
  "format_version": "1.12.0",
  "minecraft:geometry": [
    {
      "description": {
        "identifier": "geometry.m1903a1scope",
        "texture_width": 512,
        "texture_height": 256,
        "visible_bounds_width": 4,
        "visible_bounds_height": 4,
        "visible_bounds_offset": [
          0,
          1,
          0
        ]
      },
      "bones": [
        {
          "name": "root",
          "pivot": [
            0,
            0,
            0
          ],
          "cubes": [
            {
              "origin": [
                -2.5,
                19.3,
                -60
              ],
              "size": [
                1,
                3,
                43
              ],
              "uv": [
                200,
                0
              ],
              "mirror": true
            },
            {
              "origin": [
                -3.5,
                20.3,
                -60
              ],
              "size": [
                3,
                1,
                43
              ],
              "uv": [
                200,
                0
              ],
              "mirror": true
            },
            {
              "origin": [
                -2.5,
                21.8,
                -83
              ],
              "size": [
                1,
                1,
                15
              ],
              "uv": [
                200,
                0
              ],
              "mirror": true
            },
            {
              "origin": [
                -2.5,
                18.8,
                -83
              ],
              "size": [
                1,
                1,
                15
              ],
              "uv": [
                200,
                0
              ],
              "mirror": true
            },
            {
              "origin": [
                -4,
                20.3,
                -83
              ],
              "size": [
                1,
                1,
                15
              ],
              "uv": [
                200,
                0
              ],
              "mirror": true
            },
            {
              "origin": [
                -1,
                20.3,
                -83
              ],
              "size": [
                1,
                1,
                15
              ],
              "uv": [
                200,
                0
              ],
              "mirror": true
            },
            {
              "origin": [
                -3.6,
                20.3,
                -58
              ],
              "size": [
                1,
                1,
                2
              ],
              "uv": [
                200,
                0
              ],
              "mirror": true
            },
            {
              "origin": [
                -1.4,
                20.3,
                -58
              ],
              "size": [
                1,
                1,
                2
              ],
              "uv": [
                200,
                0
              ],
              "mirror": true
            },
            {
              "origin": [
                -2.5,
                21.4,
                -58
              ],
              "size": [
                1,
                1,
                2
              ],
              "uv": [
                200,
                0
              ],
              "mirror": true
            },
            {
              "origin": [
                -2.5,
                21.4,
                -35
              ],
              "size": [
                1,
                1,
                2
              ],
              "uv": [
                200,
                0
              ],
              "mirror": true
            },
            {
              "origin": [
                -1.4,
                20.3,
                -35
              ],
              "size": [
                1,
                1,
                2
              ],
              "uv": [
                200,
                0
              ],
              "mirror": true
            },
            {
              "origin": [
                -3.6,
                20.3,
                -35
              ],
              "size": [
                1,
                1,
                2
              ],
              "uv": [
                200,
                0
              ],
              "mirror": true
            },
            {
              "origin": [
                -2.5,
                22.4,
                -57.5
              ],
              "size": [
                1,
                1,
                1
              ],
              "uv": [
                200,
                0
              ],
              "mirror": true
            },
            {
              "origin": [
                -3,
                21,
                -35
              ],
              "size": [
                2,
                3,
                2
              ],
              "uv": [
                200,
                0
              ],
              "mirror": true
            },
            {
              "origin": [
                -5,
                19.8,
                -35
              ],
              "size": [
                3,
                2,
                2
              ],
              "uv": [
                200,
                0
              ],
              "mirror": true
            }
          ]
        },
        {
          "name": "gun482",
          "pivot": [
            -1.5,
            22.3,
            -68
          ],
          "rotation": [
            0,
            0,
            45
          ],
          "cubes": [
            {
              "origin": [
                -1.5,
                21.3,
                -68
              ],
              "size": [
                1,
                1,
                51
              ],
              "uv": [
                200,
                0
              ],
              "mirror": true
            }
          ]
        },
        {
          "name": "gun483",
          "pivot": [
            -2.5,
            22.3,
            -68
          ],
          "rotation": [
            0,
            0,
            45
          ],
          "cubes": [
            {
              "origin": [
                -2.5,
                21.3,
                -68
              ],
              "size": [
                1,
                1,
                51
              ],
              "uv": [
                200,
                0
              ],
              "mirror": true
            }
          ]
        },
        {
          "name": "gun484",
          "pivot": [
            -3.5,
            21.3,
            -68
          ],
          "rotation": [
            0,
            0,
            -45
          ],
          "cubes": [
            {
              "origin": [
                -3.5,
                20.3,
                -68
              ],
              "size": [
                1,
                1,
                51
              ],
              "uv": [
                200,
                0
              ],
              "mirror": true
            }
          ]
        },
        {
          "name": "gun485",
          "pivot": [
            -3.5,
            20.3,
            -68
          ],
          "rotation": [
            0,
            0,
            -45
          ],
          "cubes": [
            {
              "origin": [
                -3.5,
                19.3,
                -68
              ],
              "size": [
                1,
                1,
                51
              ],
              "uv": [
                200,
                0
              ],
              "mirror": true
            }
          ]
        },
        {
          "name": "gun486",
          "pivot": [
            -0.5,
            21.3,
            -68
          ],
          "rotation": [
            0,
            0,
            135
          ],
          "cubes": [
            {
              "origin": [
                -0.5,
                20.3,
                -68
              ],
              "size": [
                1,
                1,
                51
              ],
              "uv": [
                200,
                0
              ],
              "mirror": true
            }
          ]
        },
        {
          "name": "gun487",
          "pivot": [
            -0.5,
            20.3,
            -68
          ],
          "rotation": [
            0,
            0,
            135
          ],
          "cubes": [
            {
              "origin": [
                -0.5,
                19.3,
                -68
              ],
              "size": [
                1,
                1,
                51
              ],
              "uv": [
                200,
                0
              ],
              "mirror": true
            }
          ]
        },
        {
          "name": "gun488",
          "pivot": [
            -1.5,
            19.3,
            -68
          ],
          "rotation": [
            0,
            0,
            -135
          ],
          "cubes": [
            {
              "origin": [
                -1.5,
                18.3,
                -68
              ],
              "size": [
                1,
                1,
                51
              ],
              "uv": [
                200,
                0
              ],
              "mirror": true
            }
          ]
        },
        {
          "name": "gun489",
          "pivot": [
            -2.5,
            19.3,
            -68
          ],
          "rotation": [
            0,
            0,
            -135
          ],
          "cubes": [
            {
              "origin": [
                -2.5,
                18.3,
                -68
              ],
              "size": [
                1,
                1,
                51
              ],
              "uv": [
                200,
                0
              ],
              "mirror": true
            }
          ]
        },
        {
          "name": "gun494",
          "pivot": [
            -4,
            21.3,
            -83
          ],
          "rotation": [
            0,
            0,
            -45
          ],
          "cubes": [
            {
              "origin": [
                -4,
                20.3,
                -83
              ],
              "size": [
                1,
                1,
                15
              ],
              "uv": [
                200,
                0
              ],
              "mirror": true
            }
          ]
        },
        {
          "name": "gun495",
          "pivot": [
            -4,
            20.3,
            -83
          ],
          "rotation": [
            0,
            0,
            -45
          ],
          "cubes": [
            {
              "origin": [
                -4,
                19.3,
                -83
              ],
              "size": [
                1,
                1,
                15
              ],
              "uv": [
                200,
                0
              ],
              "mirror": true
            }
          ]
        },
        {
          "name": "gun496",
          "pivot": [
            -2.5,
            22.8,
            -83
          ],
          "rotation": [
            0,
            0,
            45
          ],
          "cubes": [
            {
              "origin": [
                -2.5,
                20.8,
                -83
              ],
              "size": [
                1,
                2,
                15
              ],
              "uv": [
                200,
                0
              ],
              "mirror": true
            }
          ]
        },
        {
          "name": "gun497",
          "pivot": [
            -1.5,
            22.8,
            -83
          ],
          "rotation": [
            0,
            0,
            45
          ],
          "cubes": [
            {
              "origin": [
                -1.5,
                21.8,
                -83
              ],
              "size": [
                2,
                1,
                15
              ],
              "uv": [
                200,
                0
              ],
              "mirror": true
            }
          ]
        },
        {
          "name": "gun498",
          "pivot": [
            0,
            21.3,
            -83
          ],
          "rotation": [
            0,
            0,
            135
          ],
          "cubes": [
            {
              "origin": [
                0,
                20.3,
                -83
              ],
              "size": [
                1,
                1,
                15
              ],
              "uv": [
                200,
                0
              ],
              "mirror": true
            }
          ]
        },
        {
          "name": "gun499",
          "pivot": [
            0,
            20.3,
            -83
          ],
          "rotation": [
            0,
            0,
            135
          ],
          "cubes": [
            {
              "origin": [
                0,
                19.3,
                -83
              ],
              "size": [
                1,
                1,
                15
              ],
              "uv": [
                200,
                0
              ],
              "mirror": true
            }
          ]
        },
        {
          "name": "gun500",
          "pivot": [
            -1.5,
            18.8,
            -83
          ],
          "rotation": [
            0,
            0,
            -135
          ],
          "cubes": [
            {
              "origin": [
                -1.5,
                16.8,
                -83
              ],
              "size": [
                1,
                2,
                15
              ],
              "uv": [
                200,
                0
              ],
              "mirror": true
            }
          ]
        },
        {
          "name": "gun501",
          "pivot": [
            -2.5,
            18.8,
            -83
          ],
          "rotation": [
            0,
            0,
            -135
          ],
          "cubes": [
            {
              "origin": [
                -2.5,
                17.8,
                -83
              ],
              "size": [
                2,
                1,
                15
              ],
              "uv": [
                200,
                0
              ],
              "mirror": true
            }
          ]
        },
        {
          "name": "gun502",
          "pivot": [
            -2.5,
            22.8,
            -68
          ],
          "rotation": [
            3,
            0,
            0
          ],
          "cubes": [
            {
              "origin": [
                -2.5,
                21.8,
                -68
              ],
              "size": [
                1,
                1,
                10
              ],
              "uv": [
                200,
                0
              ],
              "mirror": true
            }
          ]
        },
        {
          "name": "gun503",
          "pivot": [
            -4,
            21.3,
            -68
          ],
          "rotation": [
            0,
            -3,
            0
          ],
          "cubes": [
            {
              "origin": [
                -4,
                20.3,
                -68
              ],
              "size": [
                1,
                1,
                10
              ],
              "uv": [
                200,
                0
              ],
              "mirror": true
            }
          ]
        },
        {
          "name": "gun504",
          "pivot": [
            0,
            21.3,
            -68
          ],
          "rotation": [
            0,
            93.5,
            0
          ],
          "cubes": [
            {
              "origin": [
                0,
                20.3,
                -68
              ],
              "size": [
                10,
                1,
                1
              ],
              "uv": [
                200,
                0
              ],
              "mirror": true
            }
          ]
        },
        {
          "name": "gun505",
          "pivot": [
            -2.5,
            18.8,
            -68
          ],
          "rotation": [
            -93.5,
            0,
            0
          ],
          "cubes": [
            {
              "origin": [
                -2.5,
                8.8,
                -68
              ],
              "size": [
                1,
                10,
                1
              ],
              "uv": [
                200,
                0
              ],
              "mirror": true
            }
          ]
        },
        {
          "name": "gun509",
          "pivot": [
            -1.5,
            22.4,
            -58
          ],
          "rotation": [
            0,
            0,
            45
          ],
          "cubes": [
            {
              "origin": [
                -1.5,
                21.4,
                -58
              ],
              "size": [
                1,
                1,
                2
              ],
              "uv": [
                200,
                0
              ],
              "mirror": true
            }
          ]
        },
        {
          "name": "gun510",
          "pivot": [
            -2.5,
            22.4,
            -58
          ],
          "rotation": [
            0,
            0,
            45
          ],
          "cubes": [
            {
              "origin": [
                -2.5,
                21.4,
                -58
              ],
              "size": [
                1,
                1,
                2
              ],
              "uv": [
                200,
                0
              ],
              "mirror": true
            }
          ]
        },
        {
          "name": "gun511",
          "pivot": [
            -3.6,
            21.3,
            -58
          ],
          "rotation": [
            0,
            0,
            -45
          ],
          "cubes": [
            {
              "origin": [
                -3.6,
                20.3,
                -58
              ],
              "size": [
                1,
                1,
                2
              ],
              "uv": [
                200,
                0
              ],
              "mirror": true
            }
          ]
        },
        {
          "name": "gun512",
          "pivot": [
            -3.6,
            20.3,
            -58
          ],
          "rotation": [
            0,
            0,
            -45
          ],
          "cubes": [
            {
              "origin": [
                -3.6,
                18.3,
                -58
              ],
              "size": [
                1,
                2,
                2
              ],
              "uv": [
                200,
                0
              ],
              "mirror": true
            }
          ]
        },
        {
          "name": "gun513",
          "pivot": [
            -0.4,
            21.3,
            -58
          ],
          "rotation": [
            0,
            0,
            135
          ],
          "cubes": [
            {
              "origin": [
                -0.4,
                20.3,
                -58
              ],
              "size": [
                1,
                1,
                2
              ],
              "uv": [
                200,
                0
              ],
              "mirror": true
            }
          ]
        },
        {
          "name": "gun514",
          "pivot": [
            -0.4,
            20.3,
            -58
          ],
          "rotation": [
            0,
            0,
            135
          ],
          "cubes": [
            {
              "origin": [
                -0.4,
                19.3,
                -58
              ],
              "size": [
                2,
                1,
                2
              ],
              "uv": [
                200,
                0
              ],
              "mirror": true
            }
          ]
        },
        {
          "name": "gun518",
          "pivot": [
            -2.5,
            22.4,
            -35
          ],
          "rotation": [
            0,
            0,
            45
          ],
          "cubes": [
            {
              "origin": [
                -2.5,
                21.4,
                -35
              ],
              "size": [
                1,
                1,
                2
              ],
              "uv": [
                200,
                0
              ],
              "mirror": true
            }
          ]
        },
        {
          "name": "gun519",
          "pivot": [
            -1.5,
            22.4,
            -35
          ],
          "rotation": [
            0,
            0,
            45
          ],
          "cubes": [
            {
              "origin": [
                -1.5,
                21.4,
                -35
              ],
              "size": [
                1,
                1,
                2
              ],
              "uv": [
                200,
                0
              ],
              "mirror": true
            }
          ]
        },
        {
          "name": "gun520",
          "pivot": [
            -0.4,
            21.3,
            -35
          ],
          "rotation": [
            0,
            0,
            135
          ],
          "cubes": [
            {
              "origin": [
                -0.4,
                20.3,
                -35
              ],
              "size": [
                1,
                1,
                2
              ],
              "uv": [
                200,
                0
              ],
              "mirror": true
            }
          ]
        },
        {
          "name": "gun521",
          "pivot": [
            -0.4,
            20.3,
            -35
          ],
          "rotation": [
            0,
            0,
            135
          ],
          "cubes": [
            {
              "origin": [
                -0.4,
                19.3,
                -35
              ],
              "size": [
                2,
                1,
                2
              ],
              "uv": [
                200,
                0
              ],
              "mirror": true
            }
          ]
        },
        {
          "name": "gun522",
          "pivot": [
            -3.6,
            20.3,
            -35
          ],
          "rotation": [
            0,
            0,
            -45
          ],
          "cubes": [
            {
              "origin": [
                -3.6,
                18.3,
                -35
              ],
              "size": [
                1,
                2,
                2
              ],
              "uv": [
                200,
                0
              ],
              "mirror": true
            }
          ]
        },
        {
          "name": "gun523",
          "pivot": [
            -3.6,
            21.3,
            -35
          ],
          "rotation": [
            0,
            0,
            -45
          ],
          "cubes": [
            {
              "origin": [
                -3.6,
                20.3,
                -35
              ],
              "size": [
                1,
                1,
                2
              ],
              "uv": [
                200,
                0
              ],
              "mirror": true
            }
          ]
        },
        {
          "name": "gun527",
          "pivot": [
            -1.5,
            21,
            -35
          ],
          "rotation": [
            0,
            0,
            21.3018
          ],
          "cubes": [
            {
              "origin": [
                -1.5,
                19,
                -35
              ],
              "size": [
                3,
                2,
                2
              ],
              "uv": [
                200,
                0
              ],
              "mirror": true
            }
          ]
        }
      ]
    }
  ]
}