{
  "format_version": "1.12.0",
  "minecraft:geometry": [
    {
      "description": {
        "identifier": "geometry.priscopicscope",
        "texture_width": 256,
        "texture_height": 128,
        "visible_bounds_width": 4,
        "visible_bounds_height": 4,
        "visible_bounds_offset": [
          0,
          1,
          0
        ]
      },
      "bones": [
        {
          "name": "root",
          "pivot": [
            0,
            0,
            0
          ],
          "cubes": [
            {
              "origin": [
                -1,
                9,
                1
              ],
              "size": [
                5,
                1,
                114
              ],
              "uv": [
                0,
                0
              ],
              "mirror": true
            },
            {
              "origin": [
                -1,
                19,
                1
              ],
              "size": [
                5,
                1,
                114
              ],
              "uv": [
                0,
                0
              ],
              "mirror": true
            },
            {
              "origin": [
                6,
                12,
                1
              ],
              "size": [
                1,
                5,
                114
              ],
              "uv": [
                0,
                0
              ],
              "mirror": true
            },
            {
              "origin": [
                -4,
                12,
                1
              ],
              "size": [
                1,
                5,
                114
              ],
              "uv": [
                0,
                0
              ],
              "mirror": true
            },
            {
              "origin": [
                -1,
                19.5,
                76
              ],
              "size": [
                5,
                1,
                8
              ],
              "uv": [
                0,
                0
              ],
              "mirror": true
            },
            {
              "origin": [
                -1,
                8.5,
                76
              ],
              "size": [
                5,
                1,
                8
              ],
              "uv": [
                0,
                0
              ],
              "mirror": true
            },
            {
              "origin": [
                6.5,
                12,
                76
              ],
              "size": [
                1,
                5,
                8
              ],
              "uv": [
                0,
                0
              ],
              "mirror": true
            },
            {
              "origin": [
                -4.5,
                12,
                76
              ],
              "size": [
                1,
                5,
                24
              ],
              "uv": [
                0,
                0
              ],
              "mirror": true
            },
            {
              "origin": [
                -1,
                19.5,
                61
              ],
              "size": [
                5,
                1,
                12
              ],
              "uv": [
                150,
                50
              ],
              "mirror": true
            },
            {
              "origin": [
                -1,
                8.5,
                61
              ],
              "size": [
                5,
                1,
                12
              ],
              "uv": [
                150,
                50
              ],
              "mirror": true
            },
            {
              "origin": [
                6.5,
                12,
                61
              ],
              "size": [
                1,
                5,
                12
              ],
              "uv": [
                150,
                50
              ],
              "mirror": true
            },
            {
              "origin": [
                -4.5,
                12,
                61
              ],
              "size": [
                1,
                5,
                12
              ],
              "uv": [
                150,
                50
              ],
              "mirror": true
            },
            {
              "origin": [
                -4.5,
                12,
                0
              ],
              "size": [
                1,
                5,
                7
              ],
              "uv": [
                150,
                50
              ],
              "mirror": true
            },
            {
              "origin": [
                6.5,
                12,
                0
              ],
              "size": [
                1,
                5,
                7
              ],
              "uv": [
                150,
                50
              ],
              "mirror": true
            },
            {
              "origin": [
                -1,
                19.5,
                0
              ],
              "size": [
                5,
                1,
                7
              ],
              "uv": [
                150,
                50
              ],
              "mirror": true
            },
            {
              "origin": [
                -1,
                8.5,
                0
              ],
              "size": [
                5,
                1,
                7
              ],
              "uv": [
                150,
                50
              ],
              "mirror": true
            },
            {
              "origin": [
                -1,
                10,
                1.5
              ],
              "size": [
                5,
                9,
                1
              ],
              "uv": [
                150,
                0
              ],
              "mirror": true
            },
            {
              "origin": [
                -3,
                12.5,
                1.5
              ],
              "size": [
                9,
                4,
                1
              ],
              "uv": [
                150,
                0
              ],
              "mirror": true
            },
            {
              "origin": [
                6.5,
                12,
                100
              ],
              "size": [
                1,
                5,
                14
              ],
              "uv": [
                0,
                0
              ],
              "mirror": true
            },
            {
              "origin": [
                -1,
                8.5,
                100
              ],
              "size": [
                5,
                1,
                14
              ],
              "uv": [
                0,
                0
              ],
              "mirror": true
            },
            {
              "origin": [
                -1,
                19.5,
                100
              ],
              "size": [
                5,
                1,
                14
              ],
              "uv": [
                0,
                0
              ],
              "mirror": true
            },
            {
              "origin": [
                -4.5,
                12,
                100
              ],
              "size": [
                1,
                5,
                14
              ],
              "uv": [
                0,
                0
              ],
              "mirror": true
            },
            {
              "origin": [
                -1,
                19.5,
                115
              ],
              "size": [
                5,
                1,
                9
              ],
              "uv": [
                150,
                50
              ],
              "mirror": true
            },
            {
              "origin": [
                6.5,
                12,
                115
              ],
              "size": [
                1,
                5,
                9
              ],
              "uv": [
                150,
                50
              ],
              "mirror": true
            },
            {
              "origin": [
                -1,
                8.5,
                115
              ],
              "size": [
                5,
                1,
                9
              ],
              "uv": [
                150,
                50
              ],
              "mirror": true
            },
            {
              "origin": [
                -4.5,
                12,
                115
              ],
              "size": [
                1,
                5,
                9
              ],
              "uv": [
                150,
                50
              ],
              "mirror": true
            },
            {
              "origin": [
                -2,
                21.5,
                146
              ],
              "size": [
                7,
                1,
                17
              ],
              "uv": [
                150,
                50
              ],
              "mirror": true
            },
            {
              "origin": [
                -2,
                6.5,
                146
              ],
              "size": [
                7,
                1,
                17
              ],
              "uv": [
                150,
                50
              ],
              "mirror": true
            },
            {
              "origin": [
                -6.5,
                11,
                146
              ],
              "size": [
                1,
                7,
                17
              ],
              "uv": [
                150,
                50
              ],
              "mirror": true
            },
            {
              "origin": [
                8.5,
                11,
                146
              ],
              "size": [
                1,
                7,
                17
              ],
              "uv": [
                150,
                50
              ],
              "mirror": true
            },
            {
              "origin": [
                -2,
                7.5,
                160
              ],
              "size": [
                7,
                1,
                2
              ],
              "uv": [
                0,
                0
              ],
              "mirror": true
            },
            {
              "origin": [
                -2,
                20.5,
                160
              ],
              "size": [
                7,
                1,
                2
              ],
              "uv": [
                0,
                0
              ],
              "mirror": true
            },
            {
              "origin": [
                -5.5,
                11,
                160
              ],
              "size": [
                1,
                7,
                2
              ],
              "uv": [
                0,
                0
              ],
              "mirror": true
            },
            {
              "origin": [
                7.5,
                11,
                160
              ],
              "size": [
                1,
                7,
                2
              ],
              "uv": [
                0,
                0
              ],
              "mirror": true
            },
            {
              "origin": [
                0.5,
                20.5,
                66
              ],
              "size": [
                2,
                2,
                2
              ],
              "uv": [
                150,
                50
              ],
              "mirror": true
            },
            {
              "origin": [
                -2.5,
                17.5,
                24
              ],
              "size": [
                8,
                6,
                16
              ],
              "uv": [
                150,
                50
              ],
              "mirror": true
            },
            {
              "origin": [
                -3.5,
                22.5,
                27
              ],
              "size": [
                10,
                2,
                10
              ],
              "uv": [
                150,
                50
              ],
              "mirror": true
            },
            {
              "origin": [
                -2.5,
                22.5,
                26
              ],
              "size": [
                8,
                2,
                1
              ],
              "uv": [
                150,
                50
              ],
              "mirror": true
            },
            {
              "origin": [
                -2.5,
                22.5,
                37
              ],
              "size": [
                8,
                2,
                1
              ],
              "uv": [
                150,
                50
              ],
              "mirror": true
            },
            {
              "origin": [
                -4.5,
                22.5,
                28
              ],
              "size": [
                1,
                2,
                8
              ],
              "uv": [
                150,
                50
              ],
              "mirror": true
            },
            {
              "origin": [
                6.5,
                22.5,
                28
              ],
              "size": [
                1,
                2,
                8
              ],
              "uv": [
                150,
                50
              ],
              "mirror": true
            },
            {
              "origin": [
                -6,
                13.5,
                23
              ],
              "size": [
                15,
                2,
                2
              ],
              "uv": [
                0,
                0
              ],
              "mirror": true
            },
            {
              "origin": [
                -10.5,
                9.5,
                76
              ],
              "size": [
                9,
                5,
                24
              ],
              "uv": [
                0,
                0
              ],
              "mirror": true
            }
          ]
        },
        {
          "name": "PUscope5",
          "pivot": [
            4,
            20,
            1
          ],
          "rotation": [
            0,
            0,
            45
          ],
          "cubes": [
            {
              "origin": [
                4,
                19,
                1
              ],
              "size": [
                4,
                1,
                114
              ],
              "uv": [
                0,
                0
              ],
              "mirror": true
            }
          ]
        },
        {
          "name": "PUscope6",
          "pivot": [
            -1,
            20,
            1
          ],
          "rotation": [
            0,
            0,
            45
          ],
          "cubes": [
            {
              "origin": [
                -1,
                16,
                1
              ],
              "size": [
                1,
                4,
                114
              ],
              "uv": [
                0,
                0
              ],
              "mirror": true
            }
          ]
        },
        {
          "name": "PUscope7",
          "pivot": [
            7,
            12,
            1
          ],
          "rotation": [
            0,
            0,
            135
          ],
          "cubes": [
            {
              "origin": [
                7,
                11,
                1
              ],
              "size": [
                4,
                1,
                114
              ],
              "uv": [
                0,
                0
              ],
              "mirror": true
            }
          ]
        },
        {
          "name": "PUscope8",
          "pivot": [
            -4,
            12,
            1
          ],
          "rotation": [
            0,
            0,
            -45
          ],
          "cubes": [
            {
              "origin": [
                -4,
                8,
                1
              ],
              "size": [
                1,
                4,
                114
              ],
              "uv": [
                0,
                0
              ],
              "mirror": true
            }
          ]
        },
        {
          "name": "PUscope9",
          "pivot": [
            -4,
            17,
            1
          ],
          "rotation": [
            0,
            0,
            -45
          ],
          "cubes": [
            {
              "origin": [
                -4,
                16,
                1
              ],
              "size": [
                1,
                1,
                114
              ],
              "uv": [
                0,
                0
              ],
              "mirror": true
            }
          ]
        },
        {
          "name": "PUscope10",
          "pivot": [
            -1,
            9,
            1
          ],
          "rotation": [
            0,
            0,
            -135
          ],
          "cubes": [
            {
              "origin": [
                -1,
                8,
                1
              ],
              "size": [
                1,
                1,
                114
              ],
              "uv": [
                0,
                0
              ],
              "mirror": true
            }
          ]
        },
        {
          "name": "PUscope11",
          "pivot": [
            7,
            17,
            1
          ],
          "rotation": [
            0,
            0,
            135
          ],
          "cubes": [
            {
              "origin": [
                7,
                16,
                1
              ],
              "size": [
                1,
                1,
                114
              ],
              "uv": [
                0,
                0
              ],
              "mirror": true
            }
          ]
        },
        {
          "name": "PUscope12",
          "pivot": [
            4,
            9,
            1
          ],
          "rotation": [
            0,
            0,
            -135
          ],
          "cubes": [
            {
              "origin": [
                4,
                8,
                1
              ],
              "size": [
                1,
                1,
                114
              ],
              "uv": [
                0,
                0
              ],
              "mirror": true
            }
          ]
        },
        {
          "name": "PUscope17",
          "pivot": [
            -4.5,
            17,
            76
          ],
          "rotation": [
            0,
            0,
            -45
          ],
          "cubes": [
            {
              "origin": [
                -4.5,
                16,
                76
              ],
              "size": [
                5,
                1,
                8
              ],
              "uv": [
                0,
                0
              ],
              "mirror": true
            }
          ]
        },
        {
          "name": "PUscope18",
          "pivot": [
            -4.5,
            12,
            76
          ],
          "rotation": [
            0,
            0,
            -45
          ],
          "cubes": [
            {
              "origin": [
                -4.5,
                7,
                76
              ],
              "size": [
                1,
                5,
                8
              ],
              "uv": [
                0,
                0
              ],
              "mirror": true
            }
          ]
        },
        {
          "name": "PUscope19",
          "pivot": [
            4,
            20.5,
            76
          ],
          "rotation": [
            0,
            0,
            45
          ],
          "cubes": [
            {
              "origin": [
                4,
                19.5,
                76
              ],
              "size": [
                5,
                1,
                8
              ],
              "uv": [
                0,
                0
              ],
              "mirror": true
            }
          ]
        },
        {
          "name": "PUscope20",
          "pivot": [
            7.5,
            12,
            76
          ],
          "rotation": [
            0,
            0,
            135
          ],
          "cubes": [
            {
              "origin": [
                7.5,
                11,
                76
              ],
              "size": [
                5,
                1,
                8
              ],
              "uv": [
                0,
                0
              ],
              "mirror": true
            }
          ]
        },
        {
          "name": "PUscope29",
          "pivot": [
            -1,
            20.5,
            61
          ],
          "rotation": [
            0,
            0,
            45
          ],
          "cubes": [
            {
              "origin": [
                -1,
                15.5,
                61
              ],
              "size": [
                1,
                5,
                12
              ],
              "uv": [
                150,
                50
              ],
              "mirror": true
            }
          ]
        },
        {
          "name": "PUscope30",
          "pivot": [
            -1,
            20.5,
            0
          ],
          "rotation": [
            0,
            0,
            45
          ],
          "cubes": [
            {
              "origin": [
                -1,
                15.5,
                0
              ],
              "size": [
                1,
                5,
                7
              ],
              "uv": [
                150,
                50
              ],
              "mirror": true
            }
          ]
        },
        {
          "name": "PUscope31",
          "pivot": [
            -4.5,
            12,
            0
          ],
          "rotation": [
            0,
            0,
            -45
          ],
          "cubes": [
            {
              "origin": [
                -4.5,
                7,
                0
              ],
              "size": [
                1,
                5,
                7
              ],
              "uv": [
                150,
                50
              ],
              "mirror": true
            }
          ]
        },
        {
          "name": "PUscope32",
          "pivot": [
            -4.5,
            12,
            61
          ],
          "rotation": [
            0,
            0,
            -45
          ],
          "cubes": [
            {
              "origin": [
                -4.5,
                7,
                61
              ],
              "size": [
                1,
                5,
                12
              ],
              "uv": [
                150,
                50
              ],
              "mirror": true
            }
          ]
        },
        {
          "name": "PUscope33",
          "pivot": [
            4,
            20.5,
            0
          ],
          "rotation": [
            0,
            0,
            45
          ],
          "cubes": [
            {
              "origin": [
                4,
                19.5,
                0
              ],
              "size": [
                5,
                1,
                7
              ],
              "uv": [
                150,
                50
              ],
              "mirror": true
            }
          ]
        },
        {
          "name": "PUscope34",
          "pivot": [
            4,
            20.5,
            61
          ],
          "rotation": [
            0,
            0,
            45
          ],
          "cubes": [
            {
              "origin": [
                4,
                19.5,
                61
              ],
              "size": [
                5,
                1,
                12
              ],
              "uv": [
                150,
                50
              ],
              "mirror": true
            }
          ]
        },
        {
          "name": "PUscope35",
          "pivot": [
            7.5,
            12,
            0
          ],
          "rotation": [
            0,
            0,
            135
          ],
          "cubes": [
            {
              "origin": [
                7.5,
                11,
                0
              ],
              "size": [
                5,
                1,
                7
              ],
              "uv": [
                150,
                50
              ],
              "mirror": true
            }
          ]
        },
        {
          "name": "PUscope36",
          "pivot": [
            7.5,
            12,
            61
          ],
          "rotation": [
            0,
            0,
            135
          ],
          "cubes": [
            {
              "origin": [
                7.5,
                11,
                61
              ],
              "size": [
                5,
                1,
                12
              ],
              "uv": [
                150,
                50
              ],
              "mirror": true
            }
          ]
        },
        {
          "name": "PUscope43",
          "pivot": [
            -3.2,
            16.5,
            1.5
          ],
          "rotation": [
            0,
            0,
            -45
          ],
          "cubes": [
            {
              "origin": [
                -3.2,
                14.5,
                1.5
              ],
              "size": [
                4,
                2,
                1
              ],
              "uv": [
                150,
                0
              ],
              "mirror": true
            }
          ]
        },
        {
          "name": "PUscope44",
          "pivot": [
            -3.2,
            12.5,
            1.5
          ],
          "rotation": [
            0,
            0,
            -45
          ],
          "cubes": [
            {
              "origin": [
                -3.2,
                8.5,
                1.5
              ],
              "size": [
                2,
                4,
                1
              ],
              "uv": [
                150,
                0
              ],
              "mirror": true
            }
          ]
        },
        {
          "name": "PUscope45",
          "pivot": [
            6.2,
            12.5,
            1.5
          ],
          "rotation": [
            0,
            0,
            135
          ],
          "cubes": [
            {
              "origin": [
                6.2,
                10.5,
                1.5
              ],
              "size": [
                4,
                2,
                1
              ],
              "uv": [
                150,
                0
              ],
              "mirror": true
            }
          ]
        },
        {
          "name": "PUscope46",
          "pivot": [
            6.2,
            16.5,
            1.5
          ],
          "rotation": [
            0,
            0,
            135
          ],
          "cubes": [
            {
              "origin": [
                6.2,
                12.5,
                1.5
              ],
              "size": [
                2,
                4,
                1
              ],
              "uv": [
                150,
                0
              ],
              "mirror": true
            }
          ]
        },
        {
          "name": "PUscope95",
          "pivot": [
            4,
            20.5,
            100
          ],
          "rotation": [
            0,
            0,
            45
          ],
          "cubes": [
            {
              "origin": [
                4,
                19.5,
                100
              ],
              "size": [
                5,
                1,
                14
              ],
              "uv": [
                0,
                0
              ],
              "mirror": true
            }
          ]
        },
        {
          "name": "PUscope97",
          "pivot": [
            7.5,
            12,
            100
          ],
          "rotation": [
            0,
            0,
            135
          ],
          "cubes": [
            {
              "origin": [
                7.5,
                11,
                100
              ],
              "size": [
                5,
                1,
                14
              ],
              "uv": [
                0,
                0
              ],
              "mirror": true
            }
          ]
        },
        {
          "name": "PUscope100",
          "pivot": [
            -4.5,
            17,
            100
          ],
          "rotation": [
            0,
            0,
            -45
          ],
          "cubes": [
            {
              "origin": [
                -4.5,
                16,
                100
              ],
              "size": [
                5,
                1,
                14
              ],
              "uv": [
                0,
                0
              ],
              "mirror": true
            }
          ]
        },
        {
          "name": "PUscope102",
          "pivot": [
            -4.5,
            12,
            100
          ],
          "rotation": [
            0,
            0,
            -45
          ],
          "cubes": [
            {
              "origin": [
                -4.5,
                7,
                100
              ],
              "size": [
                1,
                5,
                14
              ],
              "uv": [
                0,
                0
              ],
              "mirror": true
            }
          ]
        },
        {
          "name": "PUscope103",
          "pivot": [
            -4.5,
            12,
            84
          ],
          "rotation": [
            0,
            0,
            -45
          ],
          "cubes": [
            {
              "origin": [
                -4.5,
                10,
                84
              ],
              "size": [
                1,
                2,
                16
              ],
              "uv": [
                0,
                0
              ],
              "mirror": true
            }
          ]
        },
        {
          "name": "PUscope104",
          "pivot": [
            -4.5,
            17,
            84
          ],
          "rotation": [
            0,
            0,
            -45
          ],
          "cubes": [
            {
              "origin": [
                -4.5,
                16,
                84
              ],
              "size": [
                2,
                1,
                16
              ],
              "uv": [
                0,
                0
              ],
              "mirror": true
            }
          ]
        },
        {
          "name": "PUscope106",
          "pivot": [
            4,
            20.5,
            115
          ],
          "rotation": [
            0,
            0,
            45
          ],
          "cubes": [
            {
              "origin": [
                4,
                19.5,
                115
              ],
              "size": [
                5,
                1,
                9
              ],
              "uv": [
                150,
                50
              ],
              "mirror": true
            }
          ]
        },
        {
          "name": "PUscope108",
          "pivot": [
            7.5,
            12,
            115
          ],
          "rotation": [
            0,
            0,
            135
          ],
          "cubes": [
            {
              "origin": [
                7.5,
                11,
                115
              ],
              "size": [
                5,
                1,
                9
              ],
              "uv": [
                150,
                50
              ],
              "mirror": true
            }
          ]
        },
        {
          "name": "PUscope110",
          "pivot": [
            -4.5,
            12,
            115
          ],
          "rotation": [
            0,
            0,
            -45
          ],
          "cubes": [
            {
              "origin": [
                -4.5,
                7,
                115
              ],
              "size": [
                1,
                5,
                9
              ],
              "uv": [
                150,
                50
              ],
              "mirror": true
            }
          ]
        },
        {
          "name": "PUscope112",
          "pivot": [
            -1,
            20.5,
            115
          ],
          "rotation": [
            0,
            0,
            45
          ],
          "cubes": [
            {
              "origin": [
                -1,
                15.5,
                115
              ],
              "size": [
                1,
                5,
                9
              ],
              "uv": [
                150,
                50
              ],
              "mirror": true
            }
          ]
        },
        {
          "name": "PUscope114",
          "pivot": [
            -1,
            20,
            124
          ],
          "rotation": [
            -6,
            0,
            0
          ],
          "cubes": [
            {
              "origin": [
                -1,
                18,
                124
              ],
              "size": [
                5,
                2,
                23
              ],
              "uv": [
                150,
                50
              ],
              "mirror": true
            }
          ]
        },
        {
          "name": "PUscope115",
          "pivot": [
            -4,
            17,
            124
          ],
          "rotation": [
            0,
            6,
            0
          ],
          "cubes": [
            {
              "origin": [
                -4,
                12,
                124
              ],
              "size": [
                2,
                5,
                23
              ],
              "uv": [
                150,
                50
              ],
              "mirror": true
            }
          ]
        },
        {
          "name": "PUscope116",
          "pivot": [
            6,
            17,
            124
          ],
          "rotation": [
            0,
            -6,
            0
          ],
          "cubes": [
            {
              "origin": [
                5,
                12,
                124
              ],
              "size": [
                2,
                5,
                23
              ],
              "uv": [
                150,
                50
              ],
              "mirror": true
            }
          ]
        },
        {
          "name": "PUscope117",
          "pivot": [
            -1,
            10,
            124
          ],
          "rotation": [
            6,
            0,
            0
          ],
          "cubes": [
            {
              "origin": [
                -1,
                9,
                124
              ],
              "size": [
                5,
                2,
                23
              ],
              "uv": [
                150,
                50
              ],
              "mirror": true
            }
          ]
        },
        {
          "name": "PUscope121",
          "pivot": [
            5,
            22.5,
            146
          ],
          "rotation": [
            0,
            0,
            45
          ],
          "cubes": [
            {
              "origin": [
                5,
                21.5,
                146
              ],
              "size": [
                6,
                1,
                17
              ],
              "uv": [
                150,
                50
              ],
              "mirror": true
            }
          ]
        },
        {
          "name": "PUscope122",
          "pivot": [
            -2,
            22.5,
            146
          ],
          "rotation": [
            0,
            0,
            45
          ],
          "cubes": [
            {
              "origin": [
                -2,
                16.5,
                146
              ],
              "size": [
                1,
                6,
                17
              ],
              "uv": [
                150,
                50
              ],
              "mirror": true
            }
          ]
        },
        {
          "name": "PUscope123",
          "pivot": [
            -6.5,
            11,
            146
          ],
          "rotation": [
            0,
            0,
            -45
          ],
          "cubes": [
            {
              "origin": [
                -6.5,
                5,
                146
              ],
              "size": [
                1,
                6,
                17
              ],
              "uv": [
                150,
                50
              ],
              "mirror": true
            }
          ]
        },
        {
          "name": "PUscope124",
          "pivot": [
            9.5,
            11,
            146
          ],
          "rotation": [
            0,
            0,
            135
          ],
          "cubes": [
            {
              "origin": [
                9.5,
                10,
                146
              ],
              "size": [
                6,
                1,
                17
              ],
              "uv": [
                150,
                50
              ],
              "mirror": true
            }
          ]
        },
        {
          "name": "PUscope125",
          "pivot": [
            4,
            20,
            124
          ],
          "rotation": [
            0,
            0,
            45
          ],
          "cubes": [
            {
              "origin": [
                4,
                19,
                124
              ],
              "size": [
                4,
                1,
                22
              ],
              "uv": [
                150,
                50
              ],
              "mirror": true
            }
          ]
        },
        {
          "name": "PUscope126",
          "pivot": [
            -1,
            20,
            124
          ],
          "rotation": [
            0,
            0,
            45
          ],
          "cubes": [
            {
              "origin": [
                -1,
                16,
                124
              ],
              "size": [
                1,
                4,
                22
              ],
              "uv": [
                150,
                50
              ],
              "mirror": true
            }
          ]
        },
        {
          "name": "PUscope127",
          "pivot": [
            4,
            9,
            124
          ],
          "rotation": [
            0,
            0,
            -135
          ],
          "cubes": [
            {
              "origin": [
                4,
                5,
                124
              ],
              "size": [
                1,
                4,
                22
              ],
              "uv": [
                150,
                50
              ],
              "mirror": true
            }
          ]
        },
        {
          "name": "PUscope128",
          "pivot": [
            -1,
            9,
            124
          ],
          "rotation": [
            0,
            0,
            -135
          ],
          "cubes": [
            {
              "origin": [
                -1,
                8,
                124
              ],
              "size": [
                4,
                1,
                22
              ],
              "uv": [
                150,
                50
              ],
              "mirror": true
            }
          ]
        },
        {
          "name": "PUscope129",
          "pivot": [
            4,
            7.8,
            135
          ],
          "rotation": [
            0,
            0,
            -135
          ],
          "cubes": [
            {
              "origin": [
                4,
                1.8,
                135
              ],
              "size": [
                1,
                6,
                11
              ],
              "uv": [
                150,
                50
              ],
              "mirror": true
            }
          ]
        },
        {
          "name": "PUscope130",
          "pivot": [
            4,
            21.2,
            135
          ],
          "rotation": [
            0,
            0,
            45
          ],
          "cubes": [
            {
              "origin": [
                4,
                20.2,
                135
              ],
              "size": [
                6,
                1,
                11
              ],
              "uv": [
                150,
                50
              ],
              "mirror": true
            }
          ]
        },
        {
          "name": "PUscope131",
          "pivot": [
            -1,
            21.2,
            135
          ],
          "rotation": [
            0,
            0,
            45
          ],
          "cubes": [
            {
              "origin": [
                -1,
                15.2,
                135
              ],
              "size": [
                1,
                6,
                11
              ],
              "uv": [
                150,
                50
              ],
              "mirror": true
            }
          ]
        },
        {
          "name": "PUscope132",
          "pivot": [
            -1,
            7.8,
            135
          ],
          "rotation": [
            0,
            0,
            -135
          ],
          "cubes": [
            {
              "origin": [
                -1,
                6.8,
                135
              ],
              "size": [
                6,
                1,
                11
              ],
              "uv": [
                150,
                50
              ],
              "mirror": true
            }
          ]
        },
        {
          "name": "PUscope137",
          "pivot": [
            -5,
            16.8,
            160
          ],
          "rotation": [
            0,
            0,
            -135
          ],
          "cubes": [
            {
              "origin": [
                -5,
                10.8,
                160
              ],
              "size": [
                1,
                6,
                2
              ],
              "uv": [
                0,
                0
              ],
              "mirror": true
            }
          ]
        },
        {
          "name": "PUscope138",
          "pivot": [
            -5.5,
            11.4,
            160
          ],
          "rotation": [
            0,
            0,
            -45
          ],
          "cubes": [
            {
              "origin": [
                -5.5,
                5.4,
                160
              ],
              "size": [
                1,
                6,
                2
              ],
              "uv": [
                0,
                0
              ],
              "mirror": true
            }
          ]
        },
        {
          "name": "PUscope139",
          "pivot": [
            5,
            21.2,
            160
          ],
          "rotation": [
            0,
            0,
            45
          ],
          "cubes": [
            {
              "origin": [
                5,
                20.2,
                160
              ],
              "size": [
                5,
                1,
                2
              ],
              "uv": [
                0,
                0
              ],
              "mirror": true
            }
          ]
        },
        {
          "name": "PUscope140",
          "pivot": [
            7.7,
            11.8,
            160
          ],
          "rotation": [
            0,
            0,
            45
          ],
          "cubes": [
            {
              "origin": [
                7.7,
                6.8,
                160
              ],
              "size": [
                1,
                5,
                2
              ],
              "uv": [
                0,
                0
              ],
              "mirror": true
            }
          ]
        },
        {
          "name": "PUscope141",
          "pivot": [
            9.5,
            18,
            146
          ],
          "rotation": [
            0,
            0,
            135
          ],
          "cubes": [
            {
              "origin": [
                9.5,
                17,
                146
              ],
              "size": [
                1,
                1,
                17
              ],
              "uv": [
                150,
                50
              ],
              "mirror": true
            }
          ]
        },
        {
          "name": "PUscope142",
          "pivot": [
            -6.5,
            18,
            146
          ],
          "rotation": [
            0,
            0,
            -45
          ],
          "cubes": [
            {
              "origin": [
                -6.5,
                17,
                146
              ],
              "size": [
                1,
                1,
                17
              ],
              "uv": [
                150,
                50
              ],
              "mirror": true
            }
          ]
        },
        {
          "name": "PUscope143",
          "pivot": [
            -2,
            6.5,
            146
          ],
          "rotation": [
            0,
            0,
            -135
          ],
          "cubes": [
            {
              "origin": [
                -2,
                5.5,
                146
              ],
              "size": [
                1,
                1,
                17
              ],
              "uv": [
                150,
                50
              ],
              "mirror": true
            }
          ]
        },
        {
          "name": "PUscope144",
          "pivot": [
            5,
            6.5,
            146
          ],
          "rotation": [
            0,
            0,
            -135
          ],
          "cubes": [
            {
              "origin": [
                5,
                5.5,
                146
              ],
              "size": [
                1,
                1,
                17
              ],
              "uv": [
                150,
                50
              ],
              "mirror": true
            }
          ]
        },
        {
          "name": "PUscope145",
          "pivot": [
            4.5,
            22,
            146
          ],
          "rotation": [
            0,
            0,
            45
          ],
          "cubes": [
            {
              "origin": [
                4.5,
                20,
                146
              ],
              "size": [
                7,
                2,
                1
              ],
              "uv": [
                150,
                50
              ],
              "mirror": true
            }
          ]
        },
        {
          "name": "PUscope146",
          "pivot": [
            -1.5,
            22,
            146
          ],
          "rotation": [
            0,
            0,
            45
          ],
          "cubes": [
            {
              "origin": [
                -1.5,
                15,
                146
              ],
              "size": [
                2,
                7,
                1
              ],
              "uv": [
                150,
                50
              ],
              "mirror": true
            }
          ]
        },
        {
          "name": "PUscope147",
          "pivot": [
            9.2,
            12,
            146
          ],
          "rotation": [
            0,
            0,
            135
          ],
          "cubes": [
            {
              "origin": [
                9.2,
                11,
                146
              ],
              "size": [
                7,
                1,
                1
              ],
              "uv": [
                150,
                50
              ],
              "mirror": true
            }
          ]
        },
        {
          "name": "PUscope148",
          "pivot": [
            -6.2,
            12,
            146
          ],
          "rotation": [
            0,
            0,
            -45
          ],
          "cubes": [
            {
              "origin": [
                -6.2,
                5,
                146
              ],
              "size": [
                1,
                7,
                2
              ],
              "uv": [
                150,
                50
              ],
              "mirror": true
            }
          ]
        },
        {
          "name": "PUscope151",
          "pivot": [
            -2.5,
            23.5,
            24
          ],
          "rotation": [
            30,
            0,
            0
          ],
          "cubes": [
            {
              "origin": [
                -2.5,
                17.5,
                24
              ],
              "size": [
                8,
                6,
                3
              ],
              "uv": [
                150,
                50
              ],
              "mirror": true
            }
          ]
        },
        {
          "name": "PUscope152",
          "pivot": [
            -2.5,
            23.5,
            40
          ],
          "rotation": [
            60,
            0,
            0
          ],
          "cubes": [
            {
              "origin": [
                -2.5,
                20.5,
                40
              ],
              "size": [
                8,
                3,
                6
              ],
              "uv": [
                150,
                50
              ],
              "mirror": true
            }
          ]
        }
      ]
    }
  ]
}